Metadata-Version: 2.1
Name: pychoices
Version: 0.0.3
Summary: Small Python library for receiving choice input from user.
Home-page: https://github.com/brenodega28/pychoices
Author: Breno Gomes
Author-email: brenodega28@gmail.com
License: UNKNOWN
Platform: UNKNOWN
Classifier: Programming Language :: Python :: 3
Classifier: License :: OSI Approved :: MIT License
Classifier: Operating System :: OS Independent
Requires-Python: >=3.6
